LICENSE
MANIFEST.in
README.rst
pyproject.toml
setup.cfg
setup.py
django_metamask_auth.egg-info/PKG-INFO
django_metamask_auth.egg-info/SOURCES.txt
django_metamask_auth.egg-info/dependency_links.txt
django_metamask_auth.egg-info/requires.txt
django_metamask_auth.egg-info/top_level.txt
metaMaskAuth/__init__.py
metaMaskAuth/admin.py
metaMaskAuth/api_settings.py
metaMaskAuth/apps.py
metaMaskAuth/models.py
metaMaskAuth/serializers.py
metaMaskAuth/urls.py
metaMaskAuth/utils.py
metaMaskAuth/views.py
metaMaskAuth/viewsets.py
metaMaskAuth/migrations/0001_initial.py
metaMaskAuth/migrations/__init__.py
metaMaskAuth/tests/__init__.py
metaMaskAuth/tests/test_views.py